dva_mlops_utils/__init__.py
dva_mlops_utils/service_accounts/__init__.py
dva_mlops_utils/service_accounts/service_accounts.py
dva_mlops_utils-0.0.1.dist-info/METADATA
dva_mlops_utils-0.0.1.dist-info/WHEEL
dva_mlops_utils-0.0.1.dist-info/top_level.txt
dva_mlops_utils-0.0.1.dist-info/RECORD
