Metadata-Version: 2.1
Name: dva-mlops-utils
Version: 0.0.1
Summary: Python package for utility functions and other custom Python dependencies developed internally by the DaVita MLOps team.
Author: DaVita MLOps
Author-email: MLOpsIntake&Support@davita.com
License: © 2023 DaVita Inc. All rights reserved.
Classifier: Programming Language :: Python :: 3
Classifier: Operating System :: OS Independent
Requires-Python: >=3.7
